client_analysis_cu/__init__.py
client_analysis_cu/__main__.py
client_analysis_cu-0.1.0.dist-info/METADATA
client_analysis_cu-0.1.0.dist-info/WHEEL
client_analysis_cu-0.1.0.dist-info/top_level.txt
client_analysis_cu-0.1.0.dist-info/RECORD
